JiezhuKaiyuanXiangmuXuexiRuanjiankaifa/README.md
JiezhuKaiyuanXiangmuXuexiRuanjiankaifa/__init__.py
JiezhuKaiyuanXiangmuXuexiRuanjiankaifa/__main__.py
JiezhuKaiyuanXiangmuXuexiRuanjiankaifa/file.epub
JiezhuKaiyuanXiangmuXuexiRuanjiankaifa/index.html
JiezhuKaiyuanXiangmuXuexiRuanjiankaifa/css/__init__.py
JiezhuKaiyuanXiangmuXuexiRuanjiankaifa/css/annotations.css
JiezhuKaiyuanXiangmuXuexiRuanjiankaifa/css/main.css
JiezhuKaiyuanXiangmuXuexiRuanjiankaifa/css/normalize.css
JiezhuKaiyuanXiangmuXuexiRuanjiankaifa/css/popup.css
JiezhuKaiyuanXiangmuXuexiRuanjiankaifa/font/__init__.py
JiezhuKaiyuanXiangmuXuexiRuanjiankaifa/font/fontello.eot
JiezhuKaiyuanXiangmuXuexiRuanjiankaifa/font/fontello.svg
JiezhuKaiyuanXiangmuXuexiRuanjiankaifa/font/fontello.ttf
JiezhuKaiyuanXiangmuXuexiRuanjiankaifa/font/fontello.woff
JiezhuKaiyuanXiangmuXuexiRuanjiankaifa/img/__init__.py
JiezhuKaiyuanXiangmuXuexiRuanjiankaifa/img/annotator-glyph-sprite.png
JiezhuKaiyuanXiangmuXuexiRuanjiankaifa/img/annotator-icon-sprite.png
JiezhuKaiyuanXiangmuXuexiRuanjiankaifa/img/apple-touch-icon.png
JiezhuKaiyuanXiangmuXuexiRuanjiankaifa/img/cancelfullscreen.png
JiezhuKaiyuanXiangmuXuexiRuanjiankaifa/img/close.png
JiezhuKaiyuanXiangmuXuexiRuanjiankaifa/img/fullscreen.png
JiezhuKaiyuanXiangmuXuexiRuanjiankaifa/img/loader.gif
JiezhuKaiyuanXiangmuXuexiRuanjiankaifa/img/menu-icon.png
JiezhuKaiyuanXiangmuXuexiRuanjiankaifa/img/save.png
JiezhuKaiyuanXiangmuXuexiRuanjiankaifa/img/saved.png
JiezhuKaiyuanXiangmuXuexiRuanjiankaifa/img/settings-s.png
JiezhuKaiyuanXiangmuXuexiRuanjiankaifa/img/settings.png
JiezhuKaiyuanXiangmuXuexiRuanjiankaifa/img/star.png
JiezhuKaiyuanXiangmuXuexiRuanjiankaifa/js/__init__.py
JiezhuKaiyuanXiangmuXuexiRuanjiankaifa/js/epub.js
JiezhuKaiyuanXiangmuXuexiRuanjiankaifa/js/epub.min.js
JiezhuKaiyuanXiangmuXuexiRuanjiankaifa/js/epub.min.map
JiezhuKaiyuanXiangmuXuexiRuanjiankaifa/js/hooks.min.js
JiezhuKaiyuanXiangmuXuexiRuanjiankaifa/js/hooks.min.map
jiezhu_kaiyuan_xiangmu_xuexi_ruanjiankaifa-2024.3.2.0.dist-info/METADATA
jiezhu_kaiyuan_xiangmu_xuexi_ruanjiankaifa-2024.3.2.0.dist-info/WHEEL
jiezhu_kaiyuan_xiangmu_xuexi_ruanjiankaifa-2024.3.2.0.dist-info/entry_points.txt
jiezhu_kaiyuan_xiangmu_xuexi_ruanjiankaifa-2024.3.2.0.dist-info/top_level.txt
jiezhu_kaiyuan_xiangmu_xuexi_ruanjiankaifa-2024.3.2.0.dist-info/RECORD
